MANIFEST.in
README.rst
setup.py
src/geode_solutions_wslink.egg-info/PKG-INFO
src/geode_solutions_wslink.egg-info/SOURCES.txt
src/geode_solutions_wslink.egg-info/dependency_links.txt
src/geode_solutions_wslink.egg-info/requires.txt
src/geode_solutions_wslink.egg-info/top_level.txt
src/wslink/LICENSE
src/wslink/__init__.py
src/wslink/launcher.py
src/wslink/publish.py
src/wslink/relay.py
src/wslink/server.py
src/wslink/ssl_context.py
src/wslink/uri.py
src/wslink/websocket.py
src/wslink/backends/__init__.py
src/wslink/backends/aiohttp/__init__.py
src/wslink/backends/aiohttp/launcher.py
src/wslink/backends/aiohttp/relay.py